flask_fas.py
setup.py
Flask_FAS.egg-info/PKG-INFO
Flask_FAS.egg-info/SOURCES.txt
Flask_FAS.egg-info/dependency_links.txt
Flask_FAS.egg-info/not-zip-safe
Flask_FAS.egg-info/requires.txt
Flask_FAS.egg-info/top_level.txt