Metadata-Version: 1.1
Name: Flask-FAS
Version: 0.1.0
Summary: Adds Fedora Account System support to Flask
Home-page: http://fedorahosted.org/flask-fas
Author: Ian Weller
Author-email: ianweller@fedoraproject.org
License: BSD
Platform: any
Classifier: Environment :: Web Environment
Classifier: Intended Audience :: Developers
Classifier: License :: OSI Approved :: BSD License
Classifier: Operating System :: OS Independent
Classifier: Programming Language :: Python
